{"Reviews": [{"Content": "\u9289\u6129\u5136\u9287\ue0a1\u7d87\u9287\u88e4\u4ee7\u9287\u5fcb\u4efe\u9288\u5b2a\ue196\u9287\u0441\u4eda       \u95ae\u3125\u773f\u9287\ue1bd\ue75d\u701b\u6129\u4ef9\u9287?/a>", "Date": "Sep 29, 2008", "ReviewID": "UR425662854", "Ratings": {"Service": "4", "Business service": "5", "Cleanliness": "5", "Check in / front desk": "4", "Overall": "5", "Value": "5", "Rooms": "4", "Location": "5"}, "Author": "masurao"}], "HotelInfo": {"HotelURL": "http://www.tripadvisor.com/ShowUserReviews-g297701-d1175220-r20458196-Pakir_Bungalows-Ubud_Bali.html", "HotelID": "1175220", "Price": "Unkonwn"}}