{"Reviews": [{"Content": "Great location       view from the balcony", "Date": "Jan 6, 2009", "ReviewID": "UR314602989", "Ratings": {"Service": "-1", "Business service": "-1", "Cleanliness": "-1", "Check in / front desk": "-1", "Overall": "5", "Value": "-1", "Rooms": "-1", "Location": "-1"}, "Author": "PaulaMcEwan"}], "HotelInfo": {"HotelURL": "http://www.tripadvisor.com/ShowUserReviews-g188590-d1204599-r23324848-Home_Away_Apartments-Amsterdam_Noord_Holland.html", "HotelID": "1204599", "Price": "Unkonwn"}}